league_data/__init__.py
league_data/explorer.py
league_data/league.py
league_data/models.py
league_data-1.2.3.dist-info/LICENSE.md
league_data-1.2.3.dist-info/METADATA
league_data-1.2.3.dist-info/WHEEL
league_data-1.2.3.dist-info/RECORD
