Metadata-Version: 2.1
Name: league-data
Version: 1.2.3
Summary: Tenha acesso facilmente aos dados dos campeões e skins do League of Legends.
Author: Yan Gabriel
Author-email: yangabrielogy@gmail.com
Requires-Python: >=3.11,<4.0
Classifier: Programming Language :: Python :: 3
Classifier: Programming Language :: Python :: 3.11
Requires-Dist: requests (>=2.28.2,<3.0.0)
